seq_smith-0.5.1.dist-info/RECORD
seq_smith-0.5.1.dist-info/WHEEL
seq_smith-0.5.1.dist-info/METADATA
seq_smith-0.5.1.dist-info/licenses/LICENSE
seq_smith/_seq_smith.pyi
seq_smith/_seq_smith.cpython-313-darwin.so
seq_smith/__init__.py
seq_smith/py.typed
seq_smith/python_utils.py
