Metadata-Version: 2.4
Name: seq-smith
Version: 0.5.1
Classifier: Programming Language :: Rust
Classifier: Programming Language :: Python :: 3
Classifier: Programming Language :: Python :: 3.10
Classifier: Programming Language :: Python :: 3.11
Classifier: Programming Language :: Python :: 3.12
Classifier: Programming Language :: Python :: 3.13
Classifier: License :: OSI Approved :: MIT License
Classifier: Operating System :: OS Independent
Requires-Dist: numpy
License-File: LICENSE
Summary: A Rust-based sequence alignment library for Python.
Keywords: sequence alignment,Rust,Python,bioinformatics
Author-email: Tobias Sargeant <tobias.sargeant@gmail.com>
License: MIT
Requires-Python: >=3.10
Project-URL: Homepage, https://github.com/folded/seq-smith
Project-URL: Bug Tracker, https://github.com/folded/seq-smith/issues
